BCD.v
module BCD(clk, rst_n, Q_out, Load, Bcd_in);
input clk;  //時脈訊號
input rst_n; //重制訊號
input [3:0] Bcd_in;  //Bcd輸入
input Load;          //載入訊號
output [3:0] Q_out;  //4bit 輸出
reg [3:0] Q_out; 

always@ (posedge clk)
begin
if (!rst_n)  //當reset負緣觸發時計數變為0
Q_out <= 0;
else if (Q_out == 9) //當計數到9時，將計數歸0
Q_out<= 0;
else if (Load)    //當Load正緣觸發時，將輸入的數字載入
Q_out <= Bcd_in;
else
Q_out <= Q_out + 1; //計數遞加1
end
endmodule

testbench.v
`timescale 1ns/1ps
module Testbench;
reg  clk;
reg  rst_n;
reg Load;
reg [3:0] Bcd_in;
output [3:0] Q_out;
parameter PERIOD = 20;
parameter real DUTY_CYCLE = 0.5;
parameter OFFSET = 0;
initial
begin
#OFFSET;
forever
begin
clk = 1'b0;
#(PERIOD-(PERIOD*DUTY_CYCLE)) clk = 1'b1;
#(PERIOD*DUTY_CYCLE);
end
end
initial begin
rst_n = 1'b1;      //將重置訊號設為1
#50  rst_n = 1'b0; //經過50個時間單位，將重置訊號設為0
Load = 1'b0;       //將載入訊號設為0
#50  rst_n = 1'b1; //經過50個時間單位，將重置訊號設為1
#50  Load  = 1'b1; //經過50個時間單位，將載入訊號設為1
Bcd_in = 4'b0001;  //將bcd輸入設為1
#50  Load  = 1'b0; //經過50個時間單位，將載入訊號設為0
#50  rst_n = 1'b0; //經過50個時間單位，將重置訊號設為0
#50  rst_n = 1'b1; //經過50個時間單位，將重置訊號設為1
#1000 $finish;     //經過1000個時間單位後結束
end


BCD bcd_tb(.clk(clk),.rst_n(rst_n),.Q_out(Q_out),.Load(Load),.Bcd_in(Bcd_in));
initial begin
    $dumpfile("simple.vcd");
    $dumpvars(0, bcd_tb);
end
endmodule

simple.vcd
$date
	Wed May 04 20:42:14 2022
$end
$version
	Icarus Verilog
$end
$timescale
	1ps
$end
$scope module Testbench $end
$scope module bcd_tb $end
$var wire 4 ! Bcd_in [3:0] $end
$var wire 1 " Load $end
$var wire 1 # clk $end
$var wire 1 $ rst_n $end
$var reg 4 % Q_out [3:0] $end
$upscope $end
$upscope $end
$enddefinitions $end
#0
$dumpvars
bx %
1$
0#
x"
bx !
$end
#10000
1#
#20000
0#
#30000
1#
#40000
0#
#50000
b0 %
1#
0"
0$
#60000
0#
#70000
1#
#80000
0#
#90000
1#
#100000
0#
1$
#110000
b1 %
1#
#120000
0#
#130000
b10 %
1#
#140000
0#
#150000
b1 %
1#
b1 !
1"
#160000
0#
#170000
1#
#180000
0#
#190000
1#
#200000
0#
0"
#210000
b10 %
1#
#220000
0#
#230000
b11 %
1#
#240000
0#
#250000
b0 %
1#
0$
#260000
0#
#270000
1#
#280000
0#
#290000
1#
#300000
0#
1$
#310000
b1 %
1#
#320000
0#
#330000
b10 %
1#
#340000
0#
#350000
b11 %
1#
#360000
0#
#370000
b100 %
1#
#380000
0#
#390000
b101 %
1#
#400000
0#
#410000
b110 %
1#
#420000
0#
#430000
b111 %
1#
#440000
0#
#450000
b1000 %
1#
#460000
0#
#470000
b1001 %
1#
#480000
0#
#490000
b0 %
1#
#500000
0#
#510000
b1 %
1#
#520000
0#
#530000
b10 %
1#
#540000
0#
#550000
b11 %
1#
#560000
0#
#570000
b100 %
1#
#580000
0#
#590000
b101 %
1#
#600000
0#
#610000
b110 %
1#
#620000
0#
#630000
b111 %
1#
#640000
0#
#650000
b1000 %
1#
#660000
0#
#670000
b1001 %
1#
#680000
0#
#690000
b0 %
1#
#700000
0#
#710000
b1 %
1#
#720000
0#
#730000
b10 %
1#
#740000
0#
#750000
b11 %
1#
#760000
0#
#770000
b100 %
1#
#780000
0#
#790000
b101 %
1#
#800000
0#
#810000
b110 %
1#
#820000
0#
#830000
b111 %
1#
#840000
0#
#850000
b1000 %
1#
#860000
0#
#870000
b1001 %
1#
#880000
0#
#890000
b0 %
1#
#900000
0#
#910000
b1 %
1#
#920000
0#
#930000
b10 %
1#
#940000
0#
#950000
b11 %
1#
#960000
0#
#970000
b100 %
1#
#980000
0#
#990000
b101 %
1#
#1000000
0#
#1010000
b110 %
1#
#1020000
0#
#1030000
b111 %
1#
#1040000
0#
#1050000
b1000 %
1#
#1060000
0#
#1070000
b1001 %
1#
#1080000
0#
#1090000
b0 %
1#
#1100000
0#
#1110000
b1 %
1#
#1120000
0#
#1130000
b10 %
1#
#1140000
0#
#1150000
b11 %
1#
#1160000
0#
#1170000
b100 %
1#
#1180000
0#
#1190000
b101 %
1#
#1200000
0#
#1210000
b110 %
1#
#1220000
0#
#1230000
b111 %
1#
#1240000
0#
#1250000
b1000 %
1#
#1260000
0#
#1270000
b1001 %
1#
#1280000
0#
#1290000
b0 %
1#
